sprotocol/__init__.py
sprotocol/device.py
sprotocol-0.0.3.dist-info/LICENSE
sprotocol-0.0.3.dist-info/METADATA
sprotocol-0.0.3.dist-info/WHEEL
sprotocol-0.0.3.dist-info/RECORD
