Metadata-Version: 2.1
Name: sprotocol
Version: 0.0.3
Summary: For interfacing with Brooks Instrument Mass Flow Controllers, Meters, and Pressure Controllers with S-Protocol over RS-485.
License: MIT
Author: Darren Weinhold
Requires-Python: >=3.09,<4.0
Classifier: License :: OSI Approved :: MIT License
Classifier: Programming Language :: Python :: 3
Classifier: Programming Language :: Python :: 3.9
Classifier: Programming Language :: Python :: 3.10
Classifier: Programming Language :: Python :: 3.11
Classifier: Programming Language :: Python :: 3.12
Requires-Dist: pyserial (>=3.5,<4.0)
